HyperbackupAPI2/HyperbackupAPI2_NPP.py
HyperbackupAPI2/__init__.py
HyperbackupAPI2/__main__.py
HyperbackupAPI2_NPP-0.1.5.dist-info/METADATA
HyperbackupAPI2_NPP-0.1.5.dist-info/WHEEL
HyperbackupAPI2_NPP-0.1.5.dist-info/entry_points.txt
HyperbackupAPI2_NPP-0.1.5.dist-info/top_level.txt
HyperbackupAPI2_NPP-0.1.5.dist-info/RECORD
