Metadata-Version: 2.1
Name: HyperbackupAPI2-NPP
Version: 0.1.5
Summary: API Basica per a synologys Hyperbackup
Home-page: https://github.com/NilPujolPorta/HyperbackupAPI2
Author: Nil Pujol Porta
Author-email: nilpujolporta@gmail.com
License: GNU
Platform: UNKNOWN
Requires-Dist: argparse
Requires-Dist: setuptools (>=42)
Requires-Dist: wheel
Requires-Dist: pyyaml
Requires-Dist: requests
Requires-Dist: mysql-connector-python
Requires-Dist: selenium
